pyzik/FJMoodl.py
pyzik/Sql.py
pyzik/U12.py
pyzik/__init__.py
pyzik/anim.py
pyzik/atom.py
pyzik/cmie.py
pyzik/exif.py
pyzik/faudio.py
pyzik/fmenu.py
pyzik/fserial.py
pyzik/fxkcd.py
pyzik/gsheet.py
pyzik/img.py
pyzik/menu.py
pyzik/molecule.py
pyzik/noel.py
pyzik/numly.py
pyzik/pandly.py
pyzik/parabolic.py
pyzik/quiz.py
pyzik/reaction2.py
pyzik/score.py
pyzik/scoreEther.py
pyzik/spectral.py
pyzik/spring.py
pyzik/test.py
pyzik/vector.py
pyzik-2.1.40.dist-info/LICENSE
pyzik-2.1.40.dist-info/METADATA
pyzik-2.1.40.dist-info/WHEEL
pyzik-2.1.40.dist-info/top_level.txt
pyzik-2.1.40.dist-info/RECORD
