Metadata-Version: 2.1
Name: pyzik
Version: 2.1.40
Summary: functions packages for my physic's students
Home-page: UNKNOWN
Author: FJ
Author-email: fredericboltzmann@gmail.com
License: UNKNOWN
Platform: UNKNOWN
Classifier: Programming Language :: Python :: 3
Classifier: License :: OSI Approved :: MIT License
Classifier: Operating System :: OS Independent
Classifier: Topic :: Scientific/Engineering :: Physics
Classifier: Topic :: Scientific/Engineering :: Visualization
Requires-Dist: uncertainties
Requires-Dist: astroquery
Requires-Dist: ezsheets
Requires-Dist: mendeleev (==0.4.5)
Requires-Dist: wget
Requires-Dist: chempy
Requires-Dist: sti-LabJackPython
Requires-Dist: art
Requires-Dist: cirpy
Requires-Dist: jcamp
Requires-Dist: websocket-client
Requires-Dist: sjcl
Requires-Dist: prettytable
Requires-Dist: PubChemPy
